{
  "db_name": "PostgreSQL",
  "query": "SELECT * FROM devices WHERE topic = $1",
  "describe": {
    "columns": [
      {
        "ordinal": 0,
        "name": "device_id",
        "type_info": "Int4"
      },
      {
        "ordinal": 1,
        "name": "owner_id",
        "type_info": "Int4"
      },
      {
        "ordinal": 2,
        "name": "name",
        "type_info": "Varchar"
      },
      {
        "ordinal": 3,
        "name": "topic",
        "type_info": "Varchar"
      }
    ],
    "parameters": {
      "Left": [
        "Text"
      ]
    },
    "nullable": [
      false,
      false,
      false,
      false
    ]
  },
  "hash": "c6110de8ae431bca4451b316a41cf8ccca45385c62c0acdbdcb6ff7a39e5b4bf"
}
